thyro/__init__.py
thyro/dataset.py
thyro/feature_space.py
thyro/features.py
thyro-0.1.0a3.dist-info/DESCRIPTION.rst
thyro-0.1.0a3.dist-info/METADATA
thyro-0.1.0a3.dist-info/RECORD
thyro-0.1.0a3.dist-info/WHEEL
thyro-0.1.0a3.dist-info/metadata.json
thyro-0.1.0a3.dist-info/top_level.txt
