Metadata-Version: 2.0
Name: thyro
Version: 0.1.0a3
Summary: Create feature spaces from time series data for machine learning
Home-page: https://github.com/rwhitt2049/thyro
Author: Ry Whittington
Author-email: rwhitt2049@gmail.com
License: MIT
Keywords: time_series,timeseries,iot,sensor
Platform: UNKNOWN
Classifier: Development Status :: 4 - Beta
Classifier: Intended Audience :: Developers
Classifier: Intended Audience :: Science/Research
Classifier: License :: OSI Approved :: MIT License
Classifier: Operating System :: Microsoft :: Windows
Classifier: Operating System :: POSIX
Classifier: Programming Language :: Python :: 3.3
Classifier: Programming Language :: Python :: 3.4
Classifier: Programming Language :: Python :: 3.5
Classifier: Programming Language :: Python :: 3.6
Classifier: Topic :: Scientific/Engineering
